etutils/__init__.py
etutils/asciiart.py
etutils/colormap.py
etutils/df2onehot.py
etutils/dict2flatten.py
etutils/dummyvar.py
etutils/filefun.py
etutils/internet_status.py
etutils/ismember.py
etutils/list2flatten.py
etutils/mmap_readfile.py
etutils/nanunique.py
etutils/ones2idx.py
etutils/panel2dataframe.py
etutils/path.py
etutils/picklefast.py
etutils/set_dtypes.py
etutils/slice_array.py
etutils/sql_readfile.py
etutils/strdiff.py
etutils/strfun.py
etutils/tictoc.py
etutils/time_diff.py
etutils/time_extract.py
etutils/zip_extract.py
etutils/viz/__init__.py
etutils/viz/cap.py
etutils/viz/donutchart.py
etutils/viz/hist.py
etutils/viz/hist_bokeh.py
etutils/viz/imagesc.py
etutils/viz/rocplot.py
etutils/viz/savefig.py
etutils/viz/scatter.py
etutils/viz/scatter3.py
etutils/viz/wordcloud.py
etutils-0.1.0.dist-info/LICENSE
etutils-0.1.0.dist-info/METADATA
etutils-0.1.0.dist-info/WHEEL
etutils-0.1.0.dist-info/top_level.txt
etutils-0.1.0.dist-info/RECORD
