Metadata-Version: 2.1
Name: etutils
Version: 0.1.0
Summary: etutils is Python package with helper functions that are used across various other packages. Installing this package on itself may not be so interesting.
Home-page: https://github.com/erdogant/etutils
Author: Erdogan Taskesen
Author-email: erdogant@gmail.com
License: UNKNOWN
Download-URL: https://github.com/erdogant/etutils/archive/0.1.0.tar.gz
Platform: UNKNOWN
Classifier: Programming Language :: Python :: 3
Classifier: License :: OSI Approved :: Apache Software License
Classifier: Operating System :: OS Independent
Requires-Python: >=3
Requires-Dist: numpy
Requires-Dist: pandas
Requires-Dist: tqdm
Requires-Dist: matplotlib
Requires-Dist: path
